Lab1/4 SchematicUp/syncSchematic.v
// Copyright (C) 1991-2014 Altera Corporation. All rights reserved.
// Your use of Altera Corporation's design tools, logic functions 
// and other software and tools, and its AMPP partner logic 
// functions, and any output files from any of the foregoing 
// (including device programming or simulation files), and any 
// associated documentation or information are expressly subject 
// to the terms and conditions of the Altera Program License 
// Subscription Agreement, the Altera Quartus II License Agreement,
// the Altera MegaCore Function License Agreement, or other 
// applicable license agreement, including, without limitation, 
// that your use is for the sole purpose of programming logic 
// devices manufactured by Altera and sold by Altera or its 
// authorized distributors.  Please refer to the applicable 
// agreement for further details.

// PROGRAM		"Quartus II 64-Bit"
// VERSION		"Version 14.0.0 Build 200 06/17/2014 SJ Web Edition"
// CREATED		"Sun Apr 03 17:23:40 2016"

module syncSchematic(
	clk,
	reset,
	q
);


input wire	clk;
input wire	reset;
output wire	[3:0] q;

reg	out0;
reg	out1;
reg	out2;
reg	out3;
wire	SYNTHESIZED_WIRE_0;
wire	SYNTHESIZED_WIRE_1;
wire	SYNTHESIZED_WIRE_2;
wire	SYNTHESIZED_WIRE_3;
wire	SYNTHESIZED_WIRE_4;
wire	SYNTHESIZED_WIRE_5;
wire	SYNTHESIZED_WIRE_6;
wire	SYNTHESIZED_WIRE_7;
wire	SYNTHESIZED_WIRE_8;
wire	SYNTHESIZED_WIRE_9;

assign	SYNTHESIZED_WIRE_1 = 1;
assign	SYNTHESIZED_WIRE_3 = 1;
assign	SYNTHESIZED_WIRE_6 = 1;
assign	SYNTHESIZED_WIRE_8 = 1;




always@(posedge clk or negedge reset or negedge SYNTHESIZED_WIRE_1)
begin
if (!reset)
	begin
	out0 <= 0;
	end
else
if (!SYNTHESIZED_WIRE_1)
	begin
	out0 <= 1;
	end
else
	begin
	out0 <= SYNTHESIZED_WIRE_0;
	end
end


always@(posedge clk or negedge reset or negedge SYNTHESIZED_WIRE_3)
begin
if (!reset)
	begin
	out1 <= 0;
	end
else
if (!SYNTHESIZED_WIRE_3)
	begin
	out1 <= 1;
	end
else
	begin
	out1 <= SYNTHESIZED_WIRE_2;
	end
end

assign	SYNTHESIZED_WIRE_9 = out1 & out0;

assign	SYNTHESIZED_WIRE_7 = out3 ^ SYNTHESIZED_WIRE_4;

assign	SYNTHESIZED_WIRE_4 = out2 & out1 & out0;

assign	SYNTHESIZED_WIRE_0 =  ~out0;


always@(posedge clk or negedge reset or negedge SYNTHESIZED_WIRE_6)
begin
if (!reset)
	begin
	out2 <= 0;
	end
else
if (!SYNTHESIZED_WIRE_6)
	begin
	out2 <= 1;
	end
else
	begin
	out2 <= SYNTHESIZED_WIRE_5;
	end
end


always@(posedge clk or negedge reset or negedge SYNTHESIZED_WIRE_8)
begin
if (!reset)
	begin
	out3 <= 0;
	end
else
if (!SYNTHESIZED_WIRE_8)
	begin
	out3 <= 1;
	end
else
	begin
	out3 <= SYNTHESIZED_WIRE_7;
	end
end





assign	SYNTHESIZED_WIRE_2 = out1 ^ out0;

assign	SYNTHESIZED_WIRE_5 = out2 ^ SYNTHESIZED_WIRE_9;

assign	q[2] = out2;
assign	q[1] = out1;
assign	q[0] = out0;
assign	q[3] = out3;

endmodule

Lab1/4 SchematicUp/syncUp_Top.v
// Synchronous Up Counter - Counter 4 of EE 469 Lab 1, utilizes the schematic model.
// Note that this file uses Quartus synthesized Verilog, and is intended for
// use in running GTKwave on the PC.

// Written by Jack Gentsch, Jacky Wang, and Chinh Bui
// 4/3/2016 instructed by Professor Peckol

//Create a connection between the testbench and converted schematic .bdf file
`include "syncSchematic.v"

module syncUp_Top;

	// Connect the two modules
	wire [3:0] qBench;
	wire clkBench, rstBench;

	// Declare an instance of the converted schematic module
	syncSchematic mySyncSchm (.q(qBench), .clk(clkBench), .reset(rstBench));

	// Declare an instance of the tester module
	Tester aTester (clkBench, rstBench, qBench);

	// Generates waveform using iVerilog
	initial
		begin
			$dumpfile("syncSchematic.vcd");
			$dumpvars(1, mySyncSchm);
		end
endmodule

//A test module that acts as our testbench. Required for iVerilog analysis
module Tester (clkTest, rstTest, qTest);

	//Input and output decleration to connect to DUT
	output reg rstTest, clkTest;
	input [3:0] qTest;

	parameter stimDelay = 20;

	initial // Stimulus
	begin
			//Manually changing clock and applying reset
			clkTest = 0;	rstTest = 0;
			#stimDelay clkTest = ~clkTest; 
			#stimDelay clkTest = ~clkTest; rstTest = 1;
			#stimDelay clkTest = ~clkTest;
			#stimDelay clkTest = ~clkTest;
			#stimDelay clkTest = ~clkTest;
			#stimDelay clkTest = ~clkTest;
			#stimDelay clkTest = ~clkTest;
			#stimDelay clkTest = ~clkTest;
			#stimDelay clkTest = ~clkTest;
			#stimDelay clkTest = ~clkTest;
			#stimDelay clkTest = ~clkTest;
			#stimDelay clkTest = ~clkTest;
			#stimDelay clkTest = ~clkTest;
			#stimDelay clkTest = ~clkTest;
			#stimDelay clkTest = ~clkTest;
			#stimDelay clkTest = ~clkTest;
			#stimDelay clkTest = ~clkTest;
			#stimDelay clkTest = ~clkTest;
			#stimDelay clkTest = ~clkTest;
			#stimDelay clkTest = ~clkTest;
			#stimDelay clkTest = ~clkTest;
			#stimDelay clkTest = ~clkTest;
			#stimDelay clkTest = ~clkTest;
			#(2*stimDelay); 			// needed to see END of simulation
			$finish; 					// finish simulation
		end
endmodule

Lab1/4 SchematicUp/syncSchematic.vcd
$date
	Sun Apr 03 17:25:16 2016
$end
$version
	Icarus Verilog
$end
$timescale
	1s
$end
$scope module syncUp_Top $end
$scope module mySyncSchm $end
$var wire 1 ! SYNTHESIZED_WIRE_0 $end
$var wire 1 " SYNTHESIZED_WIRE_1 $end
$var wire 1 # SYNTHESIZED_WIRE_2 $end
$var wire 1 $ SYNTHESIZED_WIRE_3 $end
$var wire 1 % SYNTHESIZED_WIRE_4 $end
$var wire 1 & SYNTHESIZED_WIRE_5 $end
$var wire 1 ' SYNTHESIZED_WIRE_6 $end
$var wire 1 ( SYNTHESIZED_WIRE_7 $end
$var wire 1 ) SYNTHESIZED_WIRE_8 $end
$var wire 1 * SYNTHESIZED_WIRE_9 $end
$var wire 1 + clk $end
$var wire 1 , reset $end
$var wire 4 - q [3:0] $end
$var reg 1 . out0 $end
$var reg 1 / out1 $end
$var reg 1 0 out2 $end
$var reg 1 1 out3 $end
$upscope $end
$upscope $end
$enddefinitions $end
#0
$dumpvars
01
00
0/
0.
b0 -
0,
0+
0*
1)
0(
1'
0&
0%
1$
0#
1"
1!
$end
#20
1+
#40
1,
0+
#60
1#
0!
b1 -
1.
1+
#80
0+
#100
1!
1/
b10 -
0.
1+
#120
0+
#140
1&
0#
0!
1*
b11 -
1.
1+
#160
0+
#180
1!
0*
10
0/
b100 -
0.
1+
#200
0+
#220
1#
0!
b101 -
1.
1+
#240
0+
#260
1!
1/
b110 -
0.
1+
#280
0+
#300
1(
0&
0#
0!
1%
1*
b111 -
1.
1+
#320
0+
#340
1!
0%
0*
11
00
0/
b1000 -
0.
1+
#360
0+
#380
1#
0!
b1001 -
1.
1+
#400
0+
#420
1!
1/
b1010 -
0.
1+
#440
0+
#460
1&
0#
0!
1*
b1011 -
1.
1+
