Lab1/1 RippleDown/rippleDownCounter.v
// A four-stage ripple up counter with active low reset - Counter 1 of EE 469 Lab 1
// Note that this lower level module is the gate level model of the counter.

// Written by Jack Gentsch, Jacky Wang, and Chinh Bui
// 4/3/2016 instructed by Professor Peckol

module rippleDownCounter(out[3:0], clk, rst);

	//Attaches outputs, clock, and reset to upper level module
	output wire [3:0] out;
	wire [3:0] flip;
	input wire clk, rst;

	//Construction of flip-flops. Connected to create an asynchronous up counter.
	DFlipFlop ff0 (.q(out[0]), .qBar(flip[0]), .D(flip[0]), .clk(clk), .rst(rst));
	DFlipFlop ff1 (.q(out[1]), .qBar(flip[1]), .D(flip[1]), .clk(out[0]), .rst(rst));
	DFlipFlop ff2 (.q(out[2]), .qBar(flip[2]), .D(flip[2]), .clk(out[1]), .rst(rst));
	DFlipFlop ff3 (.q(out[3]), .qBar(flip[3]), .D(flip[3]), .clk(out[2]), .rst(rst));

endmodule

//DFlipFlop module given in lab documentation
module DFlipFlop(q, qBar, D, clk, rst);
	input D, clk, rst;
	output q, qBar;
	reg q;
	not n1 (qBar, q);
		//Note that DFF is implicitly active low reset
		always@ (negedge rst or posedge clk)
			begin
				if(!rst)
					q = 0;
				else
					q = D;
			end
endmodule

Lab1/1 RippleDown/counter_GTK.v
// A four-stage ripple down counter with active low reset- Counter 1 of EE 469 Lab 1
// Note that this upper level module is intended for use with GTKwave on the PC.

// Written by Jack Gentsch, Jacky Wang, and Chinh Bui
// 4/3/2016 instructed by Professor Peckol

//Create a connection between the testbench and converted schematic .bdf file
`include "rippleDownCounter.v"

module counter_GTK;
	// connect the two modules
	wire clk, rst;
	wire [3:0] out;

	// Declare an instance of the ripple counter module
	rippleDownCounter myRippleCounter(out[3:0], clk, rst);

	// Declare an instance of the testbench module
	Tester myTester (clk, rst, out[3:0]);

	// File specifications for gtkwave
	initial
		begin
			$dumpfile("rippleCount.vcd");
			$dumpvars(0,myRippleCounter);
		end
endmodule

//The testbench module used to apply inputs to our counter
module Tester (clk, rst, out);

	input [3:0] out;
	output reg clk, rst;
	parameter stimDelay = 20;

	initial // Creates output in CMD
	begin
		$display("\t\t Reset \t Out[3] Out[2] Out[1] Out[0] \t Time ");
		$monitor("\t\t %b\t %b \t %b \t %b", rst, out[3], out[2], out[1], out[0], $time );
	end

	initial // Stimulus, manually cycles clock
		begin
			clk = 1'b1; rst = 1'b0;
			#stimDelay clk = ~clk;
			#stimDelay clk = ~clk;
			#stimDelay clk = ~clk; rst = 1'b1;
			#stimDelay clk = ~clk;
			#stimDelay clk = ~clk;
			#stimDelay clk = ~clk;
			#stimDelay clk = ~clk;
			#stimDelay clk = ~clk;
			#stimDelay clk = ~clk;
			#stimDelay clk = ~clk;
			#stimDelay clk = ~clk;
			#stimDelay clk = ~clk;
			#stimDelay clk = ~clk;
			#stimDelay clk = ~clk;
			#stimDelay clk = ~clk;
			#stimDelay clk = ~clk;
			#stimDelay clk = ~clk;
			#stimDelay clk = ~clk;
			#stimDelay clk = ~clk;
			#stimDelay clk = ~clk;
			#stimDelay clk = ~clk;
			#stimDelay clk = ~clk;
			#stimDelay clk = ~clk;
			#stimDelay clk = ~clk;
			#stimDelay clk = ~clk;
			#stimDelay clk = ~clk;
			#stimDelay clk = ~clk;
			#stimDelay clk = ~clk;
			#stimDelay clk = ~clk;
			#stimDelay clk = ~clk;
			#stimDelay clk = ~clk;
			#stimDelay clk = ~clk;
			#stimDelay clk = ~clk;
			#stimDelay clk = ~clk;
			#stimDelay clk = ~clk;
			#stimDelay clk = ~clk;
			#stimDelay clk = ~clk;
			#stimDelay clk = ~clk;
			#stimDelay clk = ~clk;
			#stimDelay clk = ~clk;
			#stimDelay clk = ~clk;
			#stimDelay clk = ~clk;
			#stimDelay clk = ~clk;
			#stimDelay clk = ~clk;
			#stimDelay clk = ~clk;
			#stimDelay clk = ~clk;
			#stimDelay clk = ~clk;
			#stimDelay clk = ~clk;
			#stimDelay clk = ~clk;
			#stimDelay clk = ~clk;
			#stimDelay clk = ~clk;
			#stimDelay clk = ~clk;
			#stimDelay clk = ~clk;
			#stimDelay clk = ~clk;
			#stimDelay clk = ~clk;
			#stimDelay clk = ~clk;
			#stimDelay clk = ~clk;
			#stimDelay clk = ~clk;
			#stimDelay clk = ~clk;
			#stimDelay clk = ~clk;
			#stimDelay clk = ~clk;
			#stimDelay clk = ~clk;
			#stimDelay clk = ~clk;
			#stimDelay clk = ~clk;
			#stimDelay clk = ~clk;
			#stimDelay clk = ~clk;
			#stimDelay clk = ~clk;
			#stimDelay clk = ~clk;
			#stimDelay clk = ~clk;
			#stimDelay clk = ~clk;
			#stimDelay clk = ~clk;
			#stimDelay clk = ~clk;
			#(2*stimDelay); // needed to see END of simulation
			$finish; // finish simulation
		end
endmodule

Lab1/1 RippleDown/rippleCount.vcd
$date
	Sun Apr 03 15:27:02 2016
$end
$version
	Icarus Verilog
$end
$timescale
	1s
$end
$scope module counter_GTK $end
$scope module myRippleCounter $end
$var wire 1 ! rst $end
$var wire 4 " out [3:0] $end
$var wire 4 # flip [3:0] $end
$var wire 1 $ clk $end
$upscope $end
$upscope $end
$enddefinitions $end
#0
$dumpvars
1$
b1111 #
b0 "
0!
$end
#20
0$
#40
1$
#60
1!
0$
#80
b0 #
b1111 "
1$
#100
0$
#120
b1 #
b1110 "
1$
#140
0$
#160
b10 #
b1101 "
1$
#180
0$
#200
b11 #
b1100 "
1$
#220
0$
#240
b100 #
b1011 "
1$
#260
0$
#280
b101 #
b1010 "
1$
#300
0$
#320
b110 #
b1001 "
1$
#340
0$
#360
b111 #
b1000 "
1$
#380
0$
#400
b1000 #
b111 "
1$
#420
0$
#440
b1001 #
b110 "
1$
#460
0$
#480
b1010 #
b101 "
1$
#500
0$
#520
b1011 #
b100 "
1$
#540
0$
#560
b1100 #
b11 "
1$
#580
0$
#600
b1101 #
b10 "
1$
#620
0$
#640
b1110 #
b1 "
1$
#660
0$
#680
b1111 #
b0 "
1$
#700
0$
#720
b0 #
b1111 "
1$
#740
0$
#760
b1 #
b1110 "
1$
#780
0$
#800
b10 #
b1101 "
1$
#820
0$
#840
b11 #
b1100 "
1$
#860
0$
#880
b100 #
b1011 "
1$
#900
0$
#920
b101 #
b1010 "
1$
#940
0$
#960
b110 #
b1001 "
1$
#980
0$
#1000
b111 #
b1000 "
1$
#1020
0$
#1040
b1000 #
b111 "
1$
#1060
0$
#1080
b1001 #
b110 "
1$
#1100
0$
#1120
b1010 #
b101 "
1$
#1140
0$
#1160
b1011 #
b100 "
1$
#1180
0$
#1200
b1100 #
b11 "
1$
#1220
0$
#1240
b1101 #
b10 "
1$
#1260
0$
#1280
b1110 #
b1 "
1$
#1300
0$
#1320
b1111 #
b0 "
1$
#1340
0$
#1360
b0 #
b1111 "
1$
#1380
0$
#1400
b1 #
b1110 "
1$
#1420
0$
#1440
b10 #
b1101 "
1$
