Lab1/3 Johnson/syncJohn.v
// EE 469
// Coders: Chinh Bui, Jack Gentsch, Jacky Wang
// 3/31/2016

// A four stage (4 bit) synchronous Johnson counter,
// with active low reset, using a behavioural level
// model.

module syncJohn(out, clk, rst);
	output reg [3:0] out; // present state output
	input clk, rst;

	reg [3:0] ns; // next state output

	always @(*)
	begin
		ns[3] = ~out[0];
		ns[2:0] = out[3:1];
	end

	// DFF
	always @(posedge clk)
		if (!rst)
			out <= 4'b0000;	
		else
			out <= ns;

endmodule

Lab1/3 Johnson/syncJohnGTK.v
`include "syncJohn.v"

module syncJohnGTK;

	// connect the two modules
	wire [3:0] outBench;
	wire clkBench, rstBench;

	// declare an instance of the syncJohn module
	syncJohn mySyncJohn (outBench, clkBench, rstBench);

	// declare an instance of the testIt module
	Tester aTester (rstBench, clkBench, outBench);

	// file for gtkwave
	initial
		begin
			$dumpfile("syncJohn.vcd");
			$dumpvars(1, mySyncJohn);
		end
		
endmodule

module Tester (rstTest, clkTest, outTest);

	output reg rstTest, clkTest;
	input [3:0] outTest;

	parameter stimDelay = 20;

	initial // Response
	begin
		$display("\t\t rstTest clkTest outTest ");
		$monitor("\t\t %b\t %b \t %b", rstTest, clkTest, outTest );
	end

	initial // Stimulus
	begin
			clkTest = 0;	rstTest = 0;
			#stimDelay clkTest = ~clkTest; 
			#stimDelay clkTest = ~clkTest; rstTest = 1;
			#stimDelay clkTest = ~clkTest;
			#stimDelay clkTest = ~clkTest;
			#stimDelay clkTest = ~clkTest;
			#stimDelay clkTest = ~clkTest;
			#stimDelay clkTest = ~clkTest;
			#stimDelay clkTest = ~clkTest;
			#stimDelay clkTest = ~clkTest;
			#stimDelay clkTest = ~clkTest;
			#stimDelay clkTest = ~clkTest;
			#stimDelay clkTest = ~clkTest;
			#stimDelay clkTest = ~clkTest;
			#stimDelay clkTest = ~clkTest;
			#stimDelay clkTest = ~clkTest;
			#stimDelay clkTest = ~clkTest;
			#stimDelay clkTest = ~clkTest;
			#stimDelay clkTest = ~clkTest;
			#stimDelay clkTest = ~clkTest;
			#stimDelay clkTest = ~clkTest;
			#stimDelay clkTest = ~clkTest;
			#stimDelay clkTest = ~clkTest;
			#stimDelay clkTest = ~clkTest;
			#(2*stimDelay); 			// needed to see END of simulation
			$finish; 					// finish simulation
		end
endmodule

Lab1/3 Johnson/syncJohn.vcd
$date
	Fri Apr 01 15:23:57 2016
$end
$version
	Icarus Verilog
$end
$timescale
	1s
$end
$scope module syncJohnGTK $end
$scope module mySyncJohn $end
$var wire 1 ! clk $end
$var wire 1 " rst $end
$var reg 4 # ns [3:0] $end
$var reg 4 $ out [3:0] $end
$upscope $end
$upscope $end
$enddefinitions $end
#0
$dumpvars
bx $
bx #
0"
0!
$end
#20
b1000 #
b0 $
1!
#40
1"
0!
#60
b1100 #
b1000 $
1!
#80
0!
#100
b1110 #
b1100 $
1!
#120
0!
#140
b1111 #
b1110 $
1!
#160
0!
#180
b111 #
b1111 $
1!
#200
0!
#220
b11 #
b111 $
1!
#240
0!
#260
b1 #
b11 $
1!
#280
0!
#300
b0 #
b1 $
1!
#320
0!
#340
b1000 #
b0 $
1!
#360
0!
#380
b1100 #
b1000 $
1!
#400
0!
#420
b1110 #
b1100 $
1!
#440
0!
#460
b1111 #
b1110 $
1!
