Lab1/2 SyncUp/syncUp.v
// A four-stage synchrnous up counter with active low reset- Counter 1 of EE 469 Lab 1
// Note that this lower level module is the dataflow model of the counter.

// Written by Jack Gentsch, Jacky Wang, and Chinh Bui
// 4/3/2016 instructed by Professor Peckol

module syncUp(q, clk, rst);
	output [3:0] q;
	input clk, rst;
	wire [3:0] d, qb; 

	// Connecting DFFs to form a 4 bit counter
	assign d[3] = (qb[0] & q[3]) | (qb[1] & q[3]) | (qb[2] & q[3]) | (qb[3] & q[2] & q[1] & q[0]);
	DFlipFlop dff3 (q[3], qb[3], d[3], clk, rst);
	
	assign d[2] = (q[2] & qb[0]) | (qb[1] & q[2]) | (qb[2] & q[1] & q[0]);
	DFlipFlop dff2 (q[2], qb[2], d[2], clk, rst);
	
	assign d[1] = q[1] ^ q[0];
	DFlipFlop dff1 (q[1], qb[1], d[1], clk, rst);
	
	assign d[0] = qb[0];
	DFlipFlop dff0 (q[0], qb[0], d[0], clk, rst);

endmodule

// DFF
module DFlipFlop(q, qBar, D, clk, rst);
	input D, clk, rst;
	output q, qBar;
	reg q;
	not n1 (qBar, q);
		always@ (negedge rst or posedge clk)
		begin
			if(!rst)
				q = 0;
			else
				q = D;
		end
endmodule

Lab1/2 SyncUp/syncUpGTK.v
`include "syncUp.v"

module syncUpGTK;

	// connect the two modules
	wire [3:0] qBench;
	wire clkBench, rstBench;

	// declare an instance of the syncUp module
	syncUp mySyncUp (qBench, clkBench, rstBench);

	// declare an instance of the testIt module
	Tester aTester (clkBench, rstBench, qBench);

	// file for gtkwave
	initial
		begin
			$dumpfile("syncUp.vcd");
			$dumpvars(1, mySyncUp);
		end
		
endmodule

module Tester (clkTest, rstTest, qTest);

	output reg rstTest, clkTest;
	input [3:0] qTest;

	parameter stimDelay = 20;

	initial // Response
	begin
		$display("\t\t rstTest clkTest qTest ");
		$monitor("\t\t %b\t %b \t %b", rstTest, clkTest, qTest );
	end

	initial // Stimulus
	begin
			clkTest = 0;	rstTest = 0;
			#stimDelay clkTest = ~clkTest; 
			#stimDelay clkTest = ~clkTest; rstTest = 1;
			#stimDelay clkTest = ~clkTest;
			#stimDelay clkTest = ~clkTest;
			#stimDelay clkTest = ~clkTest;
			#stimDelay clkTest = ~clkTest;
			#stimDelay clkTest = ~clkTest;
			#stimDelay clkTest = ~clkTest;
			#stimDelay clkTest = ~clkTest;
			#stimDelay clkTest = ~clkTest;
			#stimDelay clkTest = ~clkTest;
			#stimDelay clkTest = ~clkTest;
			#stimDelay clkTest = ~clkTest;
			#stimDelay clkTest = ~clkTest;
			#stimDelay clkTest = ~clkTest;
			#stimDelay clkTest = ~clkTest;
			#stimDelay clkTest = ~clkTest;
			#stimDelay clkTest = ~clkTest;
			#stimDelay clkTest = ~clkTest;
			#stimDelay clkTest = ~clkTest;
			#stimDelay clkTest = ~clkTest;
			#stimDelay clkTest = ~clkTest;
			#stimDelay clkTest = ~clkTest;
			#stimDelay clkTest = ~clkTest;
			#stimDelay clkTest = ~clkTest;
			#stimDelay clkTest = ~clkTest;
			#stimDelay clkTest = ~clkTest;
			#stimDelay clkTest = ~clkTest;
			#stimDelay clkTest = ~clkTest;
			#stimDelay clkTest = ~clkTest;
			#stimDelay clkTest = ~clkTest;
			#stimDelay clkTest = ~clkTest;
			#(2*stimDelay); 			// needed to see END of simulation
			$finish; 					// finish simulation
		end
endmodule

Lab1/2 SyncUp/syncUp.vcd
$date
	Fri Apr 01 16:25:14 2016
$end
$version
	Icarus Verilog
$end
$timescale
	1s
$end
$scope module syncUpGTK $end
$scope module mySyncUp $end
$var wire 1 ! clk $end
$var wire 1 " rst $end
$var wire 4 # qb [3:0] $end
$var wire 4 $ q [3:0] $end
$var wire 4 % d [3:0] $end
$upscope $end
$upscope $end
$enddefinitions $end
#0
$dumpvars
b1 %
b0 $
b1111 #
0"
0!
$end
#20
1!
#40
1"
0!
#60
b10 %
b1110 #
b1 $
1!
#80
0!
#100
b11 %
b1101 #
b10 $
1!
#120
0!
#140
b100 %
b1100 #
b11 $
1!
#160
0!
#180
b101 %
b1011 #
b100 $
1!
#200
0!
#220
b110 %
b1010 #
b101 $
1!
#240
0!
#260
b111 %
b1001 #
b110 $
1!
#280
0!
#300
b1000 %
b1000 #
b111 $
1!
#320
0!
#340
b1001 %
b111 #
b1000 $
1!
#360
0!
#380
b1010 %
b110 #
b1001 $
1!
#400
0!
#420
b1011 %
b101 #
b1010 $
1!
#440
0!
#460
b1100 %
b100 #
b1011 $
1!
#480
0!
#500
b1101 %
b11 #
b1100 $
1!
#520
0!
#540
b1110 %
b10 #
b1101 $
1!
#560
0!
#580
b1111 %
b1 #
b1110 $
1!
#600
0!
#620
b0 %
b0 #
b1111 $
1!
